pymotorlib/BaseEncoder.py
pymotorlib/Motor.py
pymotorlib/MotorType.py
pymotorlib/PIDController.py
pymotorlib/PWMDriver.py
pymotorlib/__init__.py
pymotorlib-0.6.dist-info/LICENSE
pymotorlib-0.6.dist-info/METADATA
pymotorlib-0.6.dist-info/WHEEL
pymotorlib-0.6.dist-info/top_level.txt
pymotorlib-0.6.dist-info/RECORD
