Metadata-Version: 2.1
Name: pymotorlib
Version: 0.6
Summary: A package to run 12V DC Motors on the Raspberry Pi
Author-email: Tiernan Lindauer <tiernanxkl@gmail.com>
Project-URL: Homepage, https://github.com/T-Lind/MotorLib
Project-URL: Bug Tracker, https://github.com/T-Lind/MotorLib/issues
Classifier: Programming Language :: Python :: 3
Classifier: License :: OSI Approved :: MIT License
Classifier: Operating System :: OS Independent
Requires-Python: >=3.7
License-File: LICENSE
